stepfunctions_activity_worker/__init__.py
stepfunctions_activity_worker/activity_worker.py
stepfunctions_activity_worker/heartbeat.py
stepfunctions_activity_worker-1.1.3.dist-info/LICENSE
stepfunctions_activity_worker-1.1.3.dist-info/METADATA
stepfunctions_activity_worker-1.1.3.dist-info/WHEEL
stepfunctions_activity_worker-1.1.3.dist-info/top_level.txt
stepfunctions_activity_worker-1.1.3.dist-info/RECORD
