Metadata-Version: 2.1
Name: stepfunctions-activity-worker
Version: 1.1.3
Summary: Activity worker for performing AWS StepFunctions tasks
Home-page: https://github.com/AmberEngine/stepfunctions_activity_worker
Author: Amber Engine LLC
Author-email: developers@amberengine.com
License: UNKNOWN
Platform: UNKNOWN
Requires-Dist: boto3 (<2)
